ryn/__init__.py
ryn/update_checker.py
ryn/data/__init__.py
ryn/data/data_ingestion/__init__.py
ryn/data/data_ingestion/interface.py
ryn/data/data_ingestion/storage_handler.py
ryn/data/data_ingestion/api/__init__.py
ryn/data/data_ingestion/api/data_ingestion_test_api.py
ryn/data/data_ingestion/handlers/__init__.py
ryn/data/data_ingestion/handlers/conditions.py
ryn/data/data_ingestion/handlers/huggingface_handler.py
ryn/data/data_ingestion/handlers/kaggle_handler.py
ryn/data/data_ingestion/handlers/openml_handler.py
ryn/data/data_ingestion/handlers/s3_handler.py
ryn/data/data_ingestion/handlers/utils.py
ryn/data/data_ingestion/lakefs/__init__.py
ryn/data/data_ingestion/lakefs/lakefs_handler.py
ryn/data/data_ingestion/models/__init__.py
ryn/data/data_ingestion/models/metadata.py
ryn/data/data_ingestion/models/requests.py
ryn/model/CephS3Manager.py
ryn/model/__init__.py
ryn/model/model_registry.py
ryn/model/template.py
ryn/model/test.py
ryn/trainer/__init__.py
ryn/trainer/auto_trainer.py
ryn/trainer/config.py
ryn/trainer/trainer.py
ryn/trainer/base/__init__.py
ryn/trainer/base/base_dataset.py
ryn/trainer/base/base_model.py
ryn/trainer/tasks/__init__.py
ryn/trainer/tasks/image_classification.py
ryn/trainer/tasks/image_segmentation.py
ryn/trainer/tasks/tabular_classification.py
ryn/trainer/tasks/task_factory.py
ryn/trainer/tasks/task_registry.py
ryn/trainer/tasks/text_prediction.py
ryn/trainer/tasks/timeseries.py
ryn/trainer/tasks/tslib/__init__.py
ryn/trainer/tasks/tslib/run.py
ryn/trainer/tasks/tslib/data_provider/__init__.py
ryn/trainer/tasks/tslib/data_provider/data_factory.py
ryn/trainer/tasks/tslib/data_provider/data_loader.py
ryn/trainer/tasks/tslib/data_provider/m4.py
ryn/trainer/tasks/tslib/data_provider/uea.py
ryn/trainer/tasks/tslib/exp/__init__.py
ryn/trainer/tasks/tslib/exp/exp_anomaly_detection.py
ryn/trainer/tasks/tslib/exp/exp_basic.py
ryn/trainer/tasks/tslib/exp/exp_classification.py
ryn/trainer/tasks/tslib/exp/exp_imputation.py
ryn-0.2.18.dist-info/METADATA
ryn-0.2.18.dist-info/WHEEL
ryn-0.2.18.dist-info/top_level.txt
ryn-0.2.18.dist-info/RECORD
