Metadata-Version: 2.4
Name: ryn
Version: 0.2.18
Summary: Ryn SDK: data, model, and trainer interfaces
Home-page: https://github.com/AIP-MLOPS/rayen
Author: AIP MLOPS Team
Author-email: mohmmadweb@gmail.com
License: MIT
Classifier: Programming Language :: Python :: 3
Requires-Python: >=3.8
Provides-Extra: model
Provides-Extra: data
Provides-Extra: trainer
Provides-Extra: all
Dynamic: author
Dynamic: author-email
Dynamic: classifier
Dynamic: description
Dynamic: description-content-type
Dynamic: home-page
Dynamic: license
Dynamic: provides-extra
Dynamic: requires-python
Dynamic: summary
